watermelonCli/__init__.py
watermelonCli/message.py
watermelonCli-0.1.0.dist-info/METADATA
watermelonCli-0.1.0.dist-info/WHEEL
watermelonCli-0.1.0.dist-info/top_level.txt
watermelonCli-0.1.0.dist-info/RECORD
