Metadata-Version: 2.1
Name: watermelonCli
Version: 0.1.0
Summary: 一些关于cli的工具
Home-page: https://github.com/XiaoWangTongxue23
Author: XiaoWangTongxue
Author-email: XiaoWangTongxue0923@outlook.com
Classifier: Programming Language :: Python :: 3
Classifier: License :: OSI Approved :: MIT License
Classifier: Operating System :: OS Independent
